st_supabase_connection/__init__.py
st_supabase_connection-2.1.2.dist-info/licenses/LICENSE
st_supabase_connection-2.1.2.dist-info/METADATA
st_supabase_connection-2.1.2.dist-info/WHEEL
st_supabase_connection-2.1.2.dist-info/top_level.txt
st_supabase_connection-2.1.2.dist-info/RECORD
