Metadata-Version: 2.4
Name: st-supabase-connection
Version: 2.1.2
Summary: A Streamlit connection component for Supabase.
Home-page: https://github.com/SiddhantSadangi/st_supabase_connection
Author: Siddhant Sadangi
Author-email: siddhant.sadangi@gmail.com
Project-URL: Homepage, https://github.com/SiddhantSadangi/st_supabase_connection
Project-URL: Documentation, https://github.com/SiddhantSadangi/st_supabase_connection/blob/main/README.md
Project-URL: Funding, https://www.buymeacoffee.com/siddhantsadangi
Keywords: streamlit,supabase,connection,integration
Classifier: Environment :: Plugins
Classifier: Environment :: Web Environment
Classifier: Intended Audience :: Developers
Classifier: License :: OSI Approved :: MIT License
Classifier: Operating System :: OS Independent
Classifier: Programming Language :: Python
Classifier: Topic :: Software Development :: Libraries :: Python Modules
Classifier: Topic :: Database
Classifier: Topic :: Database :: Front-Ends
Classifier: Topic :: Software Development :: Libraries :: Python Modules
Classifier: Topic :: Software Development :: User Interfaces
Requires-Python: >=3.10
License-File: LICENSE
Requires-Dist: streamlit>=1.50
Requires-Dist: supabase>=2.22.0
Dynamic: author
Dynamic: author-email
Dynamic: classifier
Dynamic: description
Dynamic: description-content-type
Dynamic: home-page
Dynamic: keywords
Dynamic: license-file
Dynamic: project-url
Dynamic: requires-dist
Dynamic: requires-python
Dynamic: summary
